flet_abp_cli/__init__.py
flet_abp_cli/main.py
flet_abp_cli/src/__init__.py
flet_abp_cli/src/main.py
flet_abp_cli/src/router.py
flet_abp_cli/src/components/__init__.py
flet_abp_cli/src/components/forms/__init__.py
flet_abp_cli/src/components/forms/base.py
flet_abp_cli/src/components/forms/post.py
flet_abp_cli/src/components/modals/__init__.py
flet_abp_cli/src/components/modals/base.py
flet_abp_cli/src/components/modals/post_modal.py
flet_abp_cli/src/components/navbars/__init__.py
flet_abp_cli/src/components/navbars/base.py
flet_abp_cli/src/components/navbars/rail.py
flet_abp_cli/src/core/__init__.py
flet_abp_cli/src/core/config.py
flet_abp_cli/src/core/database.py
flet_abp_cli/src/models/__init__.py
flet_abp_cli/src/models/post.py
flet_abp_cli/src/repositories/__init__.py
flet_abp_cli/src/repositories/base.py
flet_abp_cli/src/repositories/post.py
flet_abp_cli/src/services/__init__.py
flet_abp_cli/src/services/post.py
flet_abp_cli/src/utils/__init__.py
flet_abp_cli/src/utils/errors.py
flet_abp_cli/src/utils/formatters.py
flet_abp_cli/src/utils/storage.py
flet_abp_cli/src/views/__init__.py
flet_abp_cli/src/views/base.py
flet_abp_cli/src/views/post.py
flet_abp_cli/src/views/post_form.py
flet_abp_cli-1.0.10.dist-info/LICENSE
flet_abp_cli-1.0.10.dist-info/METADATA
flet_abp_cli-1.0.10.dist-info/WHEEL
flet_abp_cli-1.0.10.dist-info/entry_points.txt
flet_abp_cli-1.0.10.dist-info/top_level.txt
flet_abp_cli-1.0.10.dist-info/RECORD
