Metadata-Version: 2.1
Name: flet-abp-cli
Version: 1.0.10
Summary: This is my first module
Author: ShadowP1e
Author-email: andrey.bakov.2006@gmail.com
Classifier: Programming Language :: Python :: 3.10
Classifier: License :: OSI Approved :: MIT License
Classifier: Operating System :: OS Independent
Requires-Python: >=3.10
License-File: LICENSE
Requires-Dist: click
